{
  "albums": [
    {
      "rank": 26,
      "artist": "26. John Coltrane With Eric Dolphy",
      "album": "Evenings at the Village Gate",
      "year": 2023
    },
    {
      "rank": 27,
      "artist": "27. Binker and Moses",
      "album": "Feeding the Machine",
      "year": 2022
    },
    {
      "rank": 28,
      "artist": "28. Alice Coltrane",
      "album": "The Carnegie Hall Concert",
      "year": 2024
    },
    {
      "rank": 29,
      "artist": "29. Flying Lotus",
      "album": "You're Dead!",
      "year": 2014
    },
    {
      "rank": 30,
      "artist": "30. Mark Hollis",
      "album": "Mark Hollis",
      "year": 1998
    },
    {
      "rank": 31,
      "artist": "31. Pharoah Sanders",
      "album": "Black Unity",
      "year": 1972
    },
    {
      "rank": 32,
      "artist": "32. Zara McFarlane",
      "album": "Sweet Whispers: Celebrating Sarah Vaughan",
      "year": 2024
    },
    {
      "rank": 33,
      "artist": "33. Sarathy Korwar",
      "album": "KALAK",
      "year": 2022
    },
    {
      "rank": 34,
      "artist": "34. Nala Sinephro",
      "album": "Endlessness",
      "year": 2024
    },
    {
      "rank": 35,
      "artist": "35. Esperanza Spalding",
      "album": "Emily's D+Evolution",
      "year": 2016
    },
    {
      "rank": 36,
      "artist": "36. Kamasi Washington",
      "album": "Heaven and Earth",
      "year": 2018
    },
    {
      "rank": 37,
      "artist": "37. Vijay Iyer, Linda May Han Oh & Tyshawn Sorey",
      "album": "Compassion",
      "year": 2024
    },
    {
      "rank": 38,
      "artist": "38. Amaro Freitas",
      "album": "Y'Y",
      "year": 2024
    },
    {
      "rank": 39,
      "artist": "39. Ezra Collective",
      "album": "Dance, No One's Watching",
      "year": 2024
    },
    {
      "rank": 40,
      "artist": "40. Allen Toussaint",
      "album": "The Bright Mississippi",
      "year": 2009
    },
    {
      "rank": 41,
      "artist": "41. Alice Coltrane",
      "album": "Ptah, The El Daoud",
      "year": 1970
    },
    {
      "rank": 42,
      "artist": "42. Matana Roberts",
      "album": "Coin Coin Chapter One: Gens De Couleur Libre",
      "year": 2011
    },
    {
      "rank": 43,
      "artist": "43. Gil Scott-Heron & Makaya McCraven",
      "album": "We're New Again",
      "year": 2020
    },
    {
      "rank": 44,
      "artist": "44. Natural Information Society",
      "album": "Since Time Is Gravity",
      "year": 2023
    },
    {
      "rank": 45,
      "artist": "45. Dawn Richard & Spencer Zahn",
      "album": "Pigments",
      "year": 2022
    },
    {
      "rank": 46,
      "artist": "46. Tom Waits",
      "album": "Alice",
      "year": 2002
    },
    {
      "rank": 47,
      "artist": "47. Vijay Iyer, Linda May Han Oh & Tyshawn Sorey",
      "album": "Uneasy",
      "year": 2021
    },
    {
      "rank": 48,
      "artist": "48. Shabaka and the Ancestors",
      "album": "We Are Sent Here By History",
      "year": 2020
    },
    {
      "rank": 49,
      "artist": "49. Emma-Jean Thackray",
      "album": "Yellow",
      "year": 2021
    },
    {
      "rank": 50,
      "artist": "50. Jeff Parker",
      "album": "Forfolks",
      "year": 2021
    }
  ]
}